MANIFEST.in
README.rst
setup.cfg
setup.py
blasy/__init__.py
blasy/_version.py
blasy/blasy.py
blasy.egg-info/PKG-INFO
blasy.egg-info/SOURCES.txt
blasy.egg-info/dependency_links.txt
blasy.egg-info/not-zip-safe
blasy.egg-info/requires.txt
blasy.egg-info/top_level.txt