Metadata-Version: 1.1
Name: blasy
Version: 0.1.1
Summary: Plugin functionality
Home-page: http://github.com/bristi/blasy
Author: Brian Stidsen
Author-email: brianstidsen@gmail.com
License: MIT
Keywords: plugin
Platform: UNKNOWN
Classifier: Development Status :: 3 - Alpha
Classifier: Intended Audience :: Developers
Classifier: License :: OSI Approved :: MIT License
Classifier: Programming Language :: Python :: 3.4
Classifier: Topic :: Software Development :: Libraries
